{
"type": "FeatureCollection",
"name": "ddu",
"crs": { "type": "name", "properties": { "name": "urn:ogc:def:crs:OGC:1.3:CRS84" } },
"features": [
{ "type": "Feature", "properties": { "name": "ГБДОУ детский сад №1", "address": "Санкт-Петербург, город Кронштадт, улица Посадская, дом 43", "lon": 29.758257, "lat": 59.992452 }, "geometry": { "type": "Point", "coordinates": [ 29.758257, 59.992452 ] } },
{ "type": "Feature", "properties": { "name": "ГБДОУ детский сад №4", "address": "Санкт-Петербург, город Кронштадт, улица Зосимова, дом 4, литера А.", "lon": 29.763404, "lat": 60.00083 }, "geometry": { "type": "Point", "coordinates": [ 29.763404, 60.00083 ] } },
{ "type": "Feature", "properties": { "name": "ГБДОУ детский сад №6", "address": "Санкт-Петербург, город Кронштадт, улица Флотская, дом 10а.", "lon": 29.769827, "lat": 59.996214 }, "geometry": { "type": "Point", "coordinates": [ 29.769827, 59.996214 ] } },
{ "type": "Feature", "properties": { "name": "ГБДОУ детский сад №8", "address": "Санкт-Петербург, город Кронштадт, улица Мануильского, дом 3, литера А.", "lon": 29.791396, "lat": 59.991754 }, "geometry": { "type": "Point", "coordinates": [ 29.791396, 59.991754 ] } },
{ "type": "Feature", "properties": { "name": "ГБДОУ детский сад №8", "address": "Санкт-Петербург, город Кронштадт, Лазаревский переулок, дом 4.", "lon": 29.789833, "lat": 59.989009 }, "geometry": { "type": "Point", "coordinates": [ 29.789833, 59.989009 ] } },
{ "type": "Feature", "properties": { "name": "ГБДОУ детский сад №13", "address": "Санкт-Петербург, город Кронштадт, улица Широкая, дом 20, литера А", "lon": 29.780068, "lat": 59.994769 }, "geometry": { "type": "Point", "coordinates": [ 29.780068, 59.994769 ] } },
{ "type": "Feature", "properties": { "name": "ГБДОУ детский сад №13", "address": "Санкт-Петербург, город Кронштадт, проспект Ленина, дом 49, литера А", "lon": 29.761733, "lat": 59.992123 }, "geometry": { "type": "Point", "coordinates": [ 29.761733, 59.992123 ] } },
{ "type": "Feature", "properties": { "name": "ГБДОУ детский сад №14", "address": "Санкт-Петербург, город Кронштадт, улица Всеволода Вишневского, дом 6, литера А", "lon": 29.764797, "lat": 59.996798 }, "geometry": { "type": "Point", "coordinates": [ 29.764797, 59.996798 ] } },
{ "type": "Feature", "properties": { "name": "ГБДОУ детский сад №17", "address": "Санкт-Петербург, город Кронштадт, проспект Ленина, дом 3, литера А", "lon": 29.767518, "lat": 60.000776 }, "geometry": { "type": "Point", "coordinates": [ 29.767518, 60.000776 ] } },
{ "type": "Feature", "properties": { "name": "ГБДОУ детский сад №18", "address": "Санкт-Петербург, город Кронштадт, Кронштадтское шоссе, дом 34, корпус 2, литера А", "lon": 29.72519, "lat": 60.010326 }, "geometry": { "type": "Point", "coordinates": [ 29.72519, 60.010326 ] } },
{ "type": "Feature", "properties": { "name": "ГБДОУ детский сад №18", "address": "Санкт-Петербург, город Кронштадт, улица Станюковича, дом 10, литера А", "lon": 29.719135, "lat": 60.009094 }, "geometry": { "type": "Point", "coordinates": [ 29.719135, 60.009094 ] } },
{ "type": "Feature", "properties": { "name": "ГБДОУ детский сад №18", "address": "Санкт-Петербург, город Кронштадт, улица Станюковича, дом 4, литера А", "lon": 29.723366, "lat": 60.008833 }, "geometry": { "type": "Point", "coordinates": [ 29.723366, 60.008833 ] } }
]
}
